{
	"schemaVersion": 1,
	"id": "scrollable_tooltips",
	"version": "${version}",
	"name": "Scrollable Tooltips",
	"description": "Adds the ability to scroll through tooltips that are larger than the screen",
	"authors": ["ADON15"],
	"contact": {
		"issues": "https://github.com/ADON15c/Scrollable-Tooltips/issues",
		"sources": "https://github.com/ADON15c/Scrollable-Tooltips"
	},
	"license": "MIT",
	"icon": "assets/scrollable_tooltips/icon.png",
	"environment": "client",
	"entrypoints": {
		"client": [
			"net.adon15.scrollable_tooltips.client.Scrollable_tooltipsClient"
		]
	},
	"mixins": [
		"scrollable_tooltips.mixins.json"
	],
	"depends": {
		"fabricloader": ">=0.14.5",
		"fabric": "*",
		"minecraft": "1.18.2"
	}
}
